full-adder/fa.vhdl
library IEEE;
use IEEE.std_logic_1164.all;

entity fa is
port(
a,b,cin : IN std_logic;
sum,carry : OUT std_logic);
end fa;

architecture behavioral of fa is
begin

sum <= (a xor b) xor cin;
carry <= (a and b) or (b and cin) or (cin and a);
end behavioral;

full-adder/fa_tb.vhdl
library IEEE;
use IEEE.std_logic_1164.all;

entity fa_tb is
end entity;

architecture behavioral of fa_tb is
component fa is
port(
a,b,cin : in std_logic;
sum,carry : out std_logic);
end component;

signal a,b,cin,sum,carry : std_logic;

begin

uut : fa port map(
a =>a,
b =>b,
cin => cin,
sum =>sum,
carry => carry);

stim : process 
begin

a <= '0';
b <= '0';
cin <= '0';
wait for 10 ns;
assert ((sum = '0') and (carry = '0'))
report "test failed for input combination 000" severity error;

a <= '0';
b <= '0';
cin <= '1';
wait for 10 ns;
assert ((sum = '1') and (carry = '0'))
report "test failed for input combination 001" severity error;

a <= '0';
b <= '1';
cin <= '0';
wait for 10 ns;
assert ((sum = '1') and (carry = '0'))
report "test failed for input combination 010" severity error;

a <= '0';
b <= '1';
cin <= '1';
wait for 10 ns;
assert ((sum = '0') and (carry = '1'))
report "test failed for input combination 011" severity error;

a <= '1';
b <= '0';
cin <= '0';
wait for 10 ns;
assert ((sum = '1') and (carry = '0'))
report "test failed for input combination 100" severity error;

a <= '1';
b <= '0';
cin <= '1';
wait for 10 ns;
assert ((sum = '0') and (carry = '1'))
report "test failed for input combination 101" severity error;

a <= '1';
b <= '1';
cin <= '0';
wait for 10 ns;
assert ((sum = '0') and (carry = '1'))
report "test failed for input combination 110" severity error;

a <= '1';
b <= '1';
cin <= '1';
wait for 10 ns;
assert ((sum = '1') and (carry = '1'))
report "test failed for input combination 111" severity error;
wait;

end process;
end behavioral;

full-adder/fa.vcd
$date
  Tue Feb  9 18:44:18 2021
$end
$version
  GHDL v0
$end
$timescale
  1 fs
$end
$scope module standard $end
$upscope $end
$scope module std_logic_1164 $end
$upscope $end
$scope module fa_tb $end
$var reg 1 ! a $end
$var reg 1 " b $end
$var reg 1 # cin $end
$var reg 1 $ sum $end
$var reg 1 % carry $end
$scope module uut $end
$var reg 1 & a $end
$var reg 1 ' b $end
$var reg 1 ( cin $end
$var reg 1 ) sum $end
$var reg 1 * carry $end
$upscope $end
$upscope $end
$enddefinitions $end
#0
0!
0"
0#
0$
0%
0&
0'
0(
0)
0*
#10000000
1#
1$
1(
1)
#20000000
1"
0#
1'
0(
#30000000
1#
0$
1%
1(
0)
1*
#40000000
1!
0"
0#
1$
0%
1&
0'
0(
1)
0*
#50000000
1#
0$
1%
1(
0)
1*
#60000000
1"
0#
1'
0(
#70000000
1#
1$
1(
1)
